{
  "environment": "web",
  "format": "html",
  "prefix": "https://storage.googleapis.com",
  "mainga": "UA-49880327-14",
  "updated": "2020-03-14T07:24:15Z",
  "id": "bashyam_blooms",
  "duration": 0,
  "title": "Bhashyam Blooms School, Guntur,Andhra Pradesh,522007",
  "authors": "\u003cName\u003e",
  "summary": "Bashyam Blooms -  QtSchool",
  "source": "1XF4Jym_RiJPApubT5WFpvlwrYuk3Jnoo8STq0fhpSQU",
  "theme": "schools",
  "status": [
    "review"
  ],
  "category": [
    "schools",
    "Telangana"
  ],
  "tags": [],
  "feedback": "qtpi.in",
  "ga": "\u003cGoogle Analytics Id\u003e",
  "url": "bashyam_blooms"
}
