{
  "environment": "web",
  "format": "html",
  "prefix": "https://storage.googleapis.com",
  "mainga": "UA-109518269-1",
  "updated": "2020-04-09T15:40:27Z",
  "id": "chaitanya_bannerghatta",
  "duration": 0,
  "title": "Sri Chaitanya Techno School (SCTS), Bannerghatta, Bangalore, Karnataka 560083",
  "authors": "\u003cName\u003e",
  "summary": "Chaitanya  -  QtSchool",
  "source": "",
  "theme": "schools",
  "status": [
    "review"
  ],
  "category": [
    "schools",
    "karnataka",
    "chaitanya"
  ],
  "tags": [],
  "feedback": "qtpi.in",
  "ga": "\u003cGoogle Analytics Id\u003e",
  "url": "chaitanya_bannerghatta"
}
